distilled/__init__.py
distilled/analysis.py
distilled/core.py
distilled/grading.py
distilled-0.1.0.dist-info/licenses/LICENSE
distilled-0.1.0.dist-info/METADATA
distilled-0.1.0.dist-info/WHEEL
distilled-0.1.0.dist-info/top_level.txt
distilled-0.1.0.dist-info/RECORD
