Metadata-Version: 2.4
Name: distilled
Version: 0.1.0
Summary: A data stream reduction middleware that maintains proportional representation
Home-page: https://github.com/yourusername/distilled
Author: Distilled Team
Author-email: Distilled Team <team@distilled.dev>
Maintainer-email: Distilled Team <team@distilled.dev>
License: MIT
Project-URL: Homepage, https://github.com/yourusername/distilled
Project-URL: Documentation, https://github.com/yourusername/distilled#readme
Project-URL: Repository, https://github.com/yourusername/distilled
Project-URL: Bug Tracker, https://github.com/yourusername/distilled/issues
Project-URL: Changelog, https://github.com/yourusername/distilled/blob/main/CHANGELOG.md
Keywords: data,stream,reduction,middleware,sampling,representation
Classifier: Development Status :: 3 - Alpha
Classifier: Intended Audience :: Developers
Classifier: License :: OSI Approved :: MIT License
Classifier: Operating System :: OS Independent
Classifier: Programming Language :: Python :: 3
Classifier: Programming Language :: Python :: 3.8
Classifier: Programming Language :: Python :: 3.9
Classifier: Programming Language :: Python :: 3.10
Classifier: Programming Language :: Python :: 3.11
Classifier: Programming Language :: Python :: 3.12
Classifier: Topic :: Software Development :: Libraries :: Python Modules
Classifier: Topic :: Scientific/Engineering :: Information Analysis
Requires-Python: >=3.8
License-File: LICENSE
Requires-Dist: numpy>=1.20.0
Requires-Dist: typing-extensions>=4.0.0
Requires-Dist: matplotlib>=3.5.0
Provides-Extra: dev
Requires-Dist: pytest>=6.0; extra == "dev"
Requires-Dist: pytest-cov>=2.0; extra == "dev"
Requires-Dist: black>=21.0; extra == "dev"
Requires-Dist: flake8>=3.8; extra == "dev"
Requires-Dist: build>=0.7.0; extra == "dev"
Requires-Dist: twine>=4.0.0; extra == "dev"
Dynamic: author
Dynamic: home-page
Dynamic: license-file
Dynamic: requires-python
